flask_tools/__init__.py
gm_flask_tools-1.3.9.dist-info/METADATA
gm_flask_tools-1.3.9.dist-info/WHEEL
gm_flask_tools-1.3.9.dist-info/top_level.txt
gm_flask_tools-1.3.9.dist-info/RECORD
