Metadata-Version: 2.1
Name: gm-flask-tools
Version: 1.3.9
Summary: A collection of useful tools for developing web pages in python/flask
Home-page: https://github.com/GrantGMiller/gm_flask_tools
Author: Grant miller
Author-email: grant@grant-miller.com
License: PSF
Project-URL: Source Code, https://github.com/GrantGMiller/gm_flask_tools
Keywords: grant miller flask tools helpers
Platform: UNKNOWN
Requires-Dist: flask
Requires-Dist: requests
